odoo/addons/l10n_fi_payment_terms/README.rst
odoo/addons/l10n_fi_payment_terms/__init__.py
odoo/addons/l10n_fi_payment_terms/__manifest__.py
odoo/addons/l10n_fi_payment_terms/data/payment_terms_finnish.xml
odoo/addons/l10n_fi_payment_terms/i18n/fi.po
odoo/addons/l10n_fi_payment_terms/i18n/l10n_fi_payment_terms.pot
odoo/addons/l10n_fi_payment_terms/models/__init__.py
odoo/addons/l10n_fi_payment_terms/models/payment_term.py
odoo/addons/l10n_fi_payment_terms/static/description/icon.png
odoo13_addon_l10n_fi_payment_terms-13.0.1.0.1.dev1.dist-info/METADATA
odoo13_addon_l10n_fi_payment_terms-13.0.1.0.1.dev1.dist-info/WHEEL
odoo13_addon_l10n_fi_payment_terms-13.0.1.0.1.dev1.dist-info/top_level.txt
odoo13_addon_l10n_fi_payment_terms-13.0.1.0.1.dev1.dist-info/RECORD
